os_aio_pod_channel/VERSION
os_aio_pod_channel/__init__.py
os_aio_pod_channel/channel.py
os_aio_pod_channel/config.py
os_aio_pod_channel/endpoint.py
os_aio_pod_channel/engine.py
os_aio_pod_channel/exceptions.py
os_aio_pod_channel/extension.py
os_aio_pod_channel/middleware.py
os_aio_pod_channel-0.1.13.dist-info/LICENSE
os_aio_pod_channel-0.1.13.dist-info/METADATA
os_aio_pod_channel-0.1.13.dist-info/WHEEL
os_aio_pod_channel-0.1.13.dist-info/top_level.txt
os_aio_pod_channel-0.1.13.dist-info/RECORD
