Metadata-Version: 2.1
Name: os-aio-pod-channel
Version: 0.1.13
Summary: A os-aio-pod component for transporting.
Home-page: https://github.com/cfhamlet/os-aio-pod-channel
Author: Ozzy
Author-email: cfhamlet@gmail.com
License: MIT License
Classifier: Development Status :: 2 - Pre-Alpha
Classifier: Intended Audience :: Developers
Classifier: License :: OSI Approved :: MIT License
Classifier: Natural Language :: English
Classifier: Programming Language :: Python :: 3
Classifier: Programming Language :: Python :: 3.6
Classifier: Programming Language :: Python :: 3.7
Classifier: Programming Language :: Python :: 3 :: Only
Classifier: Programming Language :: Python :: Implementation :: CPython
Requires-Python: >=3.6
License-File: LICENSE
Requires-Dist: os-aio-pod (>=0.1.16)
Requires-Dist: async-timeout
Requires-Dist: pydantic (>=1.8)
